.project-version
LICENSE
MANIFEST.in
README.md
pyproject.toml
setup.cfg
setup.py
intentions/__init__.py
intentions/main.py
intentions/utils.py
intentions.egg-info/PKG-INFO
intentions.egg-info/SOURCES.txt
intentions.egg-info/dependency_links.txt
intentions.egg-info/top_level.txt
intentions/render/__init__.py
intentions/render/ast_.py
intentions/render/dto.py
intentions/render/encoders.py
intentions/render/enums.py
intentions/render/main.py