Metadata-Version: 2.1
Name: intentions
Version: 0.0.9
Summary: Next-gen Arrange-Act-Assert to structure test cases and force software engineers to express explicit intentions in BDD style.
Home-page: https://github.com/dmytrostriletskyi/intentions
Author: Dmytro Striletskyi
Author-email: dmytro.striletskyi@gmail.com
License: MIT
Project-URL: Issue Tracker, https://github.com/dmytrostriletskyi/intentions/issues
Project-URL: Source Code, https://github.com/dmytrostriletskyi/intentions
Project-URL: Download, https://github.com/dmytrostriletskyi/intentions/tags
Classifier: Operating System :: OS Independent
Classifier: Intended Audience :: Developers
Classifier: License :: OSI Approved :: MIT License
Classifier: Programming Language :: Python :: 3.8
Classifier: Programming Language :: Python :: 3.9
Classifier: Programming Language :: Python :: 3.10
Classifier: Programming Language :: Python :: 3.11
License-File: LICENSE
